intro/__init__.py
intro/admin.py
intro/apps.py
intro/static/css/intro/mentor_ds.css
intro/templates/intro/_common.html
intro/templates/intro/mentor_ds.html
intro/templatetags/__init__.py
intro/templatetags/intro_tags.py
lang/__init__.py
lang/admin.py
lang/apps.py
lang/templates/lang/mentor_ds.html
lang/templatetags/__init__.py
lang/templatetags/lang_tags.py
mentor_ds/__init__.py
mentor_ds/admin.py
mentor_ds/apps.py
mentor_ds/models.py
mentor_ds/urls.py
mentor_ds/views.py
mentor_ds/migrations/__init__.py
mentor_ds/static/mentor_ds/css/navbar.css
mentor_ds/static/mentor_ds/css/style.css
mentor_ds/static/mentor_ds/css/colors/default.css
mentor_ds/static/mentor_ds/js/main.js
mentor_ds/templates/mentor_ds/base.html
mentor_ds/templates/mentor_ds/footer.html
mentor_ds/templates/mentor_ds/header.html
django_mentor_ds_extension-0.1.4.dist-info/LICENSE
django_mentor_ds_extension-0.1.4.dist-info/METADATA
django_mentor_ds_extension-0.1.4.dist-info/WHEEL
django_mentor_ds_extension-0.1.4.dist-info/top_level.txt
django_mentor_ds_extension-0.1.4.dist-info/RECORD
