Metadata-Version: 2.1
Name: django-mentor-ds-extension
Version: 0.1.4
Summary: mentor_ds extension templates for demiansoft
Home-page: https://www.demiansoft.com
Author: hyungjin kim
Author-email: hj3415@gmail.com
Project-URL: Bug Tracker, https://pypi.org/project/util-demian/
Classifier: License :: OSI Approved :: BSD License
Classifier: Operating System :: OS Independent
Classifier: Programming Language :: Python :: 3
Requires-Python: >=3.8
License-File: LICENSE
Requires-Dist: Django (>=3.2.9)
Requires-Dist: django-mentor-components (>=0.1.0)
